_kymoknot_bindings.abi3.so
kymoknot/__init__.py
kymoknot/build.py
kymoknot/knotentry.py
kymoknot/searchtype.py
kymoknot_py-0.9.dist-info/COPYING.txt
kymoknot_py-0.9.dist-info/LICENSE
kymoknot_py-0.9.dist-info/METADATA
kymoknot_py-0.9.dist-info/WHEEL
kymoknot_py-0.9.dist-info/top_level.txt
kymoknot_py-0.9.dist-info/RECORD
