Metadata-Version: 2.1
Name: kymoknot-py
Version: 0.9
Summary: Kymoknot python bindings
Home-page: https://gitlab.physics.unitn.it/giovanni.tarter/kymoknot_py
Author: Giovanni Tarter
Author-email: giovanni.tarter@unitn.it
Classifier: Programming Language :: Python :: 3
Classifier: Operating System :: OS Independent
Requires-Python: >=3.6
License-File: LICENSE
License-File: COPYING.txt
Requires-Dist: cffi (>=1.0.0)
Requires-Dist: numpy (>=1.18.5)
